LICENSE.md
MANIFEST.in
setup.py
lite_gaussian_splatting.egg-info/PKG-INFO
lite_gaussian_splatting.egg-info/SOURCES.txt
lite_gaussian_splatting.egg-info/dependency_links.txt
lite_gaussian_splatting.egg-info/requires.txt
lite_gaussian_splatting.egg-info/top_level.txt
litegs/__init__.py
litegs/arguments.py
litegs/data.py
litegs/submodules/fused_ssim/ext.cpp
litegs/submodules/fused_ssim/ssim.cu
litegs/submodules/gaussian_raster/binning.cu
litegs/submodules/gaussian_raster/compact.cu
litegs/submodules/gaussian_raster/cuda_errchk.cpp
litegs/submodules/gaussian_raster/ext_cuda.cpp
litegs/submodules/gaussian_raster/raster.cu
litegs/submodules/gaussian_raster/transform.cu
litegs/submodules/simple-knn/ext.cpp
litegs/submodules/simple-knn/simple_knn.cu
litegs/submodules/simple-knn/spatial.cu
litegs/config/__init__.py
litegs/io_manager/__init__.py
litegs/io_manager/checkpoint.py
litegs/io_manager/colmap.py
litegs/io_manager/ply.py
litegs/render/__init__.py
litegs/scene/__init__.py
litegs/scene/cluster.py
litegs/scene/point.py
litegs/submodules/fused_ssim/ext.cpp
litegs/submodules/fused_ssim/ssim.cu
litegs/submodules/fused_ssim/ssim.h
litegs/submodules/fused_ssim/fused_ssim/__init__.py
litegs/submodules/gaussian_raster/binning.cu
litegs/submodules/gaussian_raster/binning.h
litegs/submodules/gaussian_raster/compact.cu
litegs/submodules/gaussian_raster/compact.h
litegs/submodules/gaussian_raster/cuda_errchk.cpp
litegs/submodules/gaussian_raster/cuda_errchk.h
litegs/submodules/gaussian_raster/ext_cuda.cpp
litegs/submodules/gaussian_raster/raster.cu
litegs/submodules/gaussian_raster/raster.h
litegs/submodules/gaussian_raster/transform.cu
litegs/submodules/gaussian_raster/transform.h
litegs/submodules/simple-knn/ext.cpp
litegs/submodules/simple-knn/simple_knn.cu
litegs/submodules/simple-knn/simple_knn.h
litegs/submodules/simple-knn/spatial.cu
litegs/submodules/simple-knn/spatial.h
litegs/training/__init__.py
litegs/training/densify.py
litegs/training/optimizer.py
litegs/training/trainer.py
litegs/utils/__init__.py
litegs/utils/platform.py
litegs/utils/spherical_harmonics.py
litegs/utils/statistic_helper.py
litegs/utils/wrapper.py