Metadata-Version: 2.1
Name: lite-gaussian-splatting
Version: 1.0.1
Summary: A High-Performance Modular Framework for Gaussian Splatting Training
Home-page: https://github.com/MooreThreads/LiteGS
Author: Kaimin Liao
Author-email: kaiminliao@gmail.com
Classifier: Programming Language :: Python :: 3
Classifier: Operating System :: OS Independent
Requires-Python: >=3.8
License-File: LICENSE.md
